Periculum_Group_B_IE_GMBD/RiskDataframe.py
Periculum_Group_B_IE_GMBD/__init__.py
Periculum_Group_B_IE_GMBD-0.0.1.dist-info/LICENSE.txt
Periculum_Group_B_IE_GMBD-0.0.1.dist-info/METADATA
Periculum_Group_B_IE_GMBD-0.0.1.dist-info/WHEEL
Periculum_Group_B_IE_GMBD-0.0.1.dist-info/top_level.txt
Periculum_Group_B_IE_GMBD-0.0.1.dist-info/RECORD
