Metadata-Version: 2.1
Name: Periculum-Group-B-IE-GMBD
Version: 0.0.1
Summary: Risk_Based_Segmentation Package, Group Assignment
Home-page: https://github.com/setejera/Periculum_Group_B_IE_GMBD.git
Author: Sebastian Tejera, Dora Jaber,  Alejandro Kreutzer, Parma Govindsamy, Caroline Ghazzaoui 
Author-email: sebastian.tejera@student.ie.edu, parmagovindsamy@student.ie.edu, alejandro.kreutzer@student.ie.edu, dorajaber@student.ie.edu, caroline.ghazzaoui@student.ie.edu, setejera@gmail.com
License: MIT
Platform: UNKNOWN
